stackview/__init__.py
stackview/_add_bounding_boxes.py
stackview/_animate.py
stackview/_annotate.py
stackview/_bia_bob_plugins.py
stackview/_blend.py
stackview/_clusterplot.py
stackview/_colormaps.py
stackview/_context.py
stackview/_crop.py
stackview/_curtain.py
stackview/_display_range.py
stackview/_grid.py
stackview/_histogram.py
stackview/_image_widget.py
stackview/_imshow.py
stackview/_interact.py
stackview/_orthogonal.py
stackview/_picker.py
stackview/_scatterplot.py
stackview/_side_by_side.py
stackview/_slice.py
stackview/_slice_viewer.py
stackview/_sliceplot.py
stackview/_static_view.py
stackview/_switch.py
stackview/_uint_field.py
stackview/_utilities.py
stackview/_wordcloudplot.py
stackview-0.18.0.dist-info/licenses/LICENSE
stackview-0.18.0.dist-info/METADATA
stackview-0.18.0.dist-info/WHEEL
stackview-0.18.0.dist-info/entry_points.txt
stackview-0.18.0.dist-info/top_level.txt
stackview-0.18.0.dist-info/RECORD
