Metadata-Version: 2.4
Name: stackview
Version: 0.18.0
Summary: Interactive image stack viewing in jupyter notebooks
Home-page: https://github.com/haesleinhuepf/stackview/
Author: Robert Haase
Author-email: robert.haase@uni-leipzig.de
Classifier: Programming Language :: Python :: 3
Classifier: License :: OSI Approved :: BSD License
Classifier: Operating System :: OS Independent
Classifier: Intended Audience :: Science/Research
Classifier: Development Status :: 3 - Alpha
Requires-Python: >=3.6
License-File: LICENSE
Requires-Dist: numpy!=1.19.4
Requires-Dist: ipycanvas
Requires-Dist: ipywidgets
Requires-Dist: scikit-image
Requires-Dist: ipyevents
Requires-Dist: toolz
Requires-Dist: matplotlib
Requires-Dist: ipykernel
Requires-Dist: imageio
Requires-Dist: ipympl
Requires-Dist: wordcloud
Dynamic: author
Dynamic: author-email
Dynamic: classifier
Dynamic: description
Dynamic: description-content-type
Dynamic: home-page
Dynamic: license-file
Dynamic: requires-dist
Dynamic: requires-python
Dynamic: summary
